callabletools.py
callabletools-1.1.dist-info/licenses/LICENSE
callabletools-1.1.dist-info/METADATA
callabletools-1.1.dist-info/WHEEL
callabletools-1.1.dist-info/top_level.txt
callabletools-1.1.dist-info/RECORD
