Metadata-Version: 2.4
Name: callabletools
Version: 1.1
Summary: Advanced tools for callable objects in Python.
Author-email: TahsinCr <TahsinCr@outlook.com>
License: MIT
Project-URL: Homepage, https://github.com/TahsinCr/python-callabletools
Project-URL: Source, https://github.com/TahsinCr/python-callabletools
Keywords: callabletoolx,callabletools,toolx,tools,callable,argumentsignature
Classifier: Typing :: Typed
Classifier: Intended Audience :: Developers
Classifier: Programming Language :: Python :: 3
Classifier: License :: OSI Approved :: MIT License
Classifier: Operating System :: OS Independent
Requires-Python: >=3
License-File: LICENSE
Dynamic: license-file
